{
  "name": "sennenki/reisen",
  "version": "0.3.0",
  "deps": {
    "sennenki/js-ffi": "0.4.2",
    "moonbitlang/async": "0.16.6",
    "sennenki/sexp": "0.1.0",
    "Milky2018/selene": "0.32.4",
    "Milky2018/selene_raylib": "0.32.4",
    "moonbitlang/x": "0.4.43"
  },
  "readme": "README.mbt.md",
  "repository": "https://github.com/zvmsbackend/reisen.git",
  "license": "Apache-2.0",
  "keywords": [
    "game",
    "engine",
    "pixi"
  ],
  "description": "A visual novel engine in MoonBit",
  "preferred-target": "js"
}